{
  "server": [
    {
      "name": 1,
      "type": "host",
      "cpu": 2,
      "memory": 7100
    },
    {
      "name": 2,
      "type": "host",
      "cpu": 2,
      "memory": 7100
    },
    {
      "name": 3,
      "type": "host",
      "cpu": 2,
      "memory": 7100
    },
    {
      "name": 4,
      "type": "host",
      "cpu": 2,
      "memory": 7100
    },
    {
      "name": 5,
      "type": "host",
      "cpu": 2,
      "memory": 7100
    },
    {
      "name": 6,
      "type": "host",
      "cpu": 2,
      "memory": 7100
    },
    {
      "name": 7,
      "type": "host",
      "cpu": 2,
      "memory": 7100
    },
    {
      "name": 8,
      "type": "host",
      "cpu": 2,
      "memory": 7100
    },
    {
      "name": 9,
      "type": "host",
      "cpu": 2,
      "memory": 7100
    },
    {
      "name": 10,
      "type": "host",
      "cpu": 2,
      "memory": 7100
    },
    {
      "name": 11,
      "type": "host",
      "cpu": 2,
      "memory": 7100
    },
    {
      "name": 12,
      "type": "host",
      "cpu": 2,
      "memory": 7100
    }
  ],
  "link": [
    {
      "start": 1,
      "stop": 3,
      "type": "wired",
      "rate": 730.7692307692308,
      "capacity": 769.2307692307693
    },
    {
      "start": 10,
      "stop": 11,
      "type": "wired",
      "rate": 730.7692307692308,
      "capacity": 769.2307692307693
    },
    {
      "start": 10,
      "stop": 12,
      "type": "wired",
      "rate": 730.7692307692308,
      "capacity": 769.2307692307693
    },
    {
      "start": 2,
      "stop": 3,
      "type": "wired",
      "rate": 730.7692307692308,
      "capacity": 769.2307692307693
    },
    {
      "start": 3,
      "stop": 6,
      "type": "wired",
      "rate": 730.7692307692308,
      "capacity": 769.2307692307693
    },
    {
      "start": 4,
      "stop": 6,
      "type": "wired",
      "rate": 730.7692307692308,
      "capacity": 769.2307692307693
    },
    {
      "start": 5,
      "stop": 6,
      "type": "wired",
      "rate": 730.7692307692308,
      "capacity": 769.2307692307693
    },
    {
      "start": 6,
      "stop": 7,
      "type": "wired",
      "rate": 730.7692307692308,
      "capacity": 769.2307692307693
    },
    {
      "start": 6,
      "stop": 8,
      "type": "wired",
      "rate": 730.7692307692308,
      "capacity": 769.2307692307693
    },
    {
      "start": 6,
      "stop": 9,
      "type": "wired",
      "rate": 730.7692307692308,
      "capacity": 769.2307692307693
    },
    {
      "start": 7,
      "stop": 10,
      "type": "wired",
      "rate": 730.7692307692308,
      "capacity": 769.2307692307693
    },
    {
      "start": 8,
      "stop": 10,
      "type": "wired",
      "rate": 730.7692307692308,
      "capacity": 769.2307692307693
    },
    {
      "start": 9,
      "stop": 10,
      "type": "wired",
      "rate": 730.7692307692308,
      "capacity": 769.2307692307693
    }
  ],
  "flow": [
    {
      "name": "f0",
      "source": 10,
      "destination": 12,
      "rate": 1000,
      "burst": 672,
      "hops": [
        10,
        12
      ],
      "prio": "BE"
    },
    {
      "name": "f1",
      "source": 2,
      "destination": 3,
      "rate": 109971,
      "burst": 672,
      "hops": [
        2,
        3
      ],
      "prio": "BE"
    },
    {
      "name": "f2",
      "source": 9,
      "destination": 12,
      "rate": 1000,
      "burst": 672,
      "hops": [
        9,
        10,
        12
      ],
      "prio": "BE"
    },
    {
      "name": "f3",
      "source": 4,
      "destination": 6,
      "rate": 11570,
      "burst": 672,
      "hops": [
        4,
        6
      ],
      "prio": "BE"
    },
    {
      "name": "f4",
      "source": 9,
      "destination": 12,
      "rate": 1000,
      "burst": 672,
      "hops": [
        9,
        10,
        12
      ],
      "prio": "BE"
    },
    {
      "name": "f5",
      "source": 6,
      "destination": 8,
      "rate": 191753,
      "burst": 672,
      "hops": [
        6,
        8
      ],
      "prio": "BE"
    },
    {
      "name": "f6",
      "source": 4,
      "destination": 12,
      "rate": 1000,
      "burst": 672,
      "hops": [
        4,
        6,
        7,
        10,
        12
      ],
      "prio": "BE"
    },
    {
      "name": "f7",
      "source": 1,
      "destination": 10,
      "rate": 1000,
      "burst": 672,
      "hops": [
        1,
        3,
        6,
        7,
        10
      ],
      "prio": "BE"
    },
    {
      "name": "f8",
      "source": 6,
      "destination": 12,
      "rate": 1000,
      "burst": 672,
      "hops": [
        6,
        7,
        10,
        12
      ],
      "prio": "BE"
    },
    {
      "name": "f9",
      "source": 10,
      "destination": 12,
      "rate": 1000,
      "burst": 672,
      "hops": [
        10,
        12
      ],
      "prio": "BE"
    },
    {
      "name": "f10",
      "source": 9,
      "destination": 11,
      "rate": 90492,
      "burst": 672,
      "hops": [
        9,
        10,
        11
      ],
      "prio": "BE"
    },
    {
      "name": "f11",
      "source": 9,
      "destination": 12,
      "rate": 1000,
      "burst": 672,
      "hops": [
        9,
        10,
        12
      ],
      "prio": "BE"
    },
    {
      "name": "f12",
      "source": 2,
      "destination": 6,
      "rate": 1000,
      "burst": 672,
      "hops": [
        2,
        3,
        6
      ],
      "prio": "BE"
    },
    {
      "name": "f13",
      "source": 5,
      "destination": 7,
      "rate": 105955,
      "burst": 672,
      "hops": [
        5,
        6,
        7
      ],
      "prio": "BE"
    },
    {
      "name": "f14",
      "source": 6,
      "destination": 9,
      "rate": 1000,
      "burst": 672,
      "hops": [
        6,
        9
      ],
      "prio": "BE"
    },
    {
      "name": "f15",
      "source": 6,
      "destination": 12,
      "rate": 1000,
      "burst": 672,
      "hops": [
        6,
        7,
        10,
        12
      ],
      "prio": "BE"
    },
    {
      "name": "f16",
      "source": 1,
      "destination": 10,
      "rate": 1000,
      "burst": 672,
      "hops": [
        1,
        3,
        6,
        7,
        10
      ],
      "prio": "BE"
    },
    {
      "name": "f17",
      "source": 6,
      "destination": 12,
      "rate": 1000,
      "burst": 672,
      "hops": [
        6,
        7,
        10,
        12
      ],
      "prio": "BE"
    },
    {
      "name": "f18",
      "source": 5,
      "destination": 9,
      "rate": 40249,
      "burst": 672,
      "hops": [
        5,
        6,
        9
      ],
      "prio": "BE"
    },
    {
      "name": "f19",
      "source": 8,
      "destination": 12,
      "rate": 322893,
      "burst": 672,
      "hops": [
        8,
        10,
        12
      ],
      "prio": "BE"
    },
    {
      "name": "f20",
      "source": 6,
      "destination": 8,
      "rate": 1002,
      "burst": 672,
      "hops": [
        6,
        8
      ],
      "prio": "BE"
    },
    {
      "name": "f21",
      "source": 9,
      "destination": 12,
      "rate": 1000,
      "burst": 672,
      "hops": [
        9,
        10,
        12
      ],
      "prio": "BE"
    },
    {
      "name": "f22",
      "source": 3,
      "destination": 6,
      "rate": 1000,
      "burst": 672,
      "hops": [
        3,
        6
      ],
      "prio": "BE"
    },
    {
      "name": "f23",
      "source": 5,
      "destination": 12,
      "rate": 1000,
      "burst": 672,
      "hops": [
        5,
        6,
        8,
        10,
        12
      ],
      "prio": "BE"
    },
    {
      "name": "f24",
      "source": 5,
      "destination": 12,
      "rate": 1000,
      "burst": 672,
      "hops": [
        5,
        6,
        8,
        10,
        12
      ],
      "prio": "BE"
    },
    {
      "name": "f25",
      "source": 7,
      "destination": 12,
      "rate": 1000,
      "burst": 672,
      "hops": [
        7,
        10,
        12
      ],
      "prio": "BE"
    },
    {
      "name": "f26",
      "source": 1,
      "destination": 12,
      "rate": 32508,
      "burst": 672,
      "hops": [
        1,
        3,
        6,
        8,
        10,
        12
      ],
      "prio": "BE"
    },
    {
      "name": "f27",
      "source": 2,
      "destination": 3,
      "rate": 258566,
      "burst": 672,
      "hops": [
        2,
        3
      ],
      "prio": "BE"
    },
    {
      "name": "f28",
      "source": 2,
      "destination": 11,
      "rate": 1000,
      "burst": 672,
      "hops": [
        2,
        3,
        6,
        7,
        10,
        11
      ],
      "prio": "BE"
    },
    {
      "name": "f29",
      "source": 4,
      "destination": 6,
      "rate": 11563,
      "burst": 672,
      "hops": [
        4,
        6
      ],
      "prio": "BE"
    },
    {
      "name": "f30",
      "source": 10,
      "destination": 12,
      "rate": 1000,
      "burst": 672,
      "hops": [
        10,
        12
      ],
      "prio": "BE"
    },
    {
      "name": "f31",
      "source": 7,
      "destination": 11,
      "rate": 92992,
      "burst": 672,
      "hops": [
        7,
        10,
        11
      ],
      "prio": "BE"
    },
    {
      "name": "f32",
      "source": 4,
      "destination": 11,
      "rate": 24222,
      "burst": 672,
      "hops": [
        4,
        6,
        8,
        10,
        11
      ],
      "prio": "BE"
    },
    {
      "name": "f33",
      "source": 6,
      "destination": 9,
      "rate": 1000,
      "burst": 672,
      "hops": [
        6,
        9
      ],
      "prio": "BE"
    },
    {
      "name": "f34",
      "source": 7,
      "destination": 10,
      "rate": 1000,
      "burst": 672,
      "hops": [
        7,
        10
      ],
      "prio": "BE"
    },
    {
      "name": "f35",
      "source": 7,
      "destination": 11,
      "rate": 82243,
      "burst": 672,
      "hops": [
        7,
        10,
        11
      ],
      "prio": "BE"
    },
    {
      "name": "f36",
      "source": 4,
      "destination": 10,
      "rate": 1000,
      "burst": 672,
      "hops": [
        4,
        6,
        8,
        10
      ],
      "prio": "BE"
    },
    {
      "name": "f37",
      "source": 9,
      "destination": 12,
      "rate": 1000,
      "burst": 672,
      "hops": [
        9,
        10,
        12
      ],
      "prio": "BE"
    },
    {
      "name": "f38",
      "source": 6,
      "destination": 12,
      "rate": 1000,
      "burst": 672,
      "hops": [
        6,
        7,
        10,
        12
      ],
      "prio": "BE"
    },
    {
      "name": "f39",
      "source": 5,
      "destination": 6,
      "rate": 317628,
      "burst": 672,
      "hops": [
        5,
        6
      ],
      "prio": "BE"
    },
    {
      "name": "f40",
      "source": 4,
      "destination": 6,
      "rate": 11513,
      "burst": 672,
      "hops": [
        4,
        6
      ],
      "prio": "BE"
    },
    {
      "name": "f41",
      "source": 5,
      "destination": 10,
      "rate": 1000,
      "burst": 672,
      "hops": [
        5,
        6,
        8,
        10
      ],
      "prio": "BE"
    }
  ],
  "priority": {
    "A": {
      "burst": 9600,
      "crate": 100000,
      "prio": 1,
      "rate": 10000
    },
    "B": {
      "burst": 8400,
      "crate": 100000,
      "prio": 1,
      "rate": 1000
    },
    "BE": {
      "burst": 8400,
      "crate": 100000,
      "prio": 2,
      "rate": 10
    },
    "CD": {
      "burst": 9600,
      "crate": 100000,
      "prio": 0,
      "rate": 10000
    }
  }
}
